{
  "tokens_represented": {
    "OMG": {
      "weekly_open": 5.21,
      "weekly_close": 4.68,
      "weekly_delta_percentage": -10.17
    },
    "LINK": {
      "weekly_open": 18.21,
      "weekly_close": 16.12,
      "weekly_delta_percentage": -11.48
    },
    "SOL": {
      "weekly_open": 116.52,
      "weekly_close": 96.09,
      "weekly_delta_percentage": -17.53
    },
    "LPT": {
      "weekly_open": 30.37,
      "weekly_close": 29.74,
      "weekly_delta_percentage": -2.07
    },
    "ALGO": {
      "weekly_open": 1.0345,
      "weekly_close": 0.9248,
      "weekly_delta_percentage": -10.6
    },
    "XYO": {
      "weekly_open": 0.022048,
      "weekly_close": 0.022268,
      "weekly_delta_percentage": 1.0
    },
    "API3": {
      "weekly_open": 3.66,
      "weekly_close": 4.02,
      "weekly_delta_percentage": 9.84
    },
    "SKL": {
      "weekly_open": 0.1329,
      "weekly_close": 0.1477,
      "weekly_delta_percentage": 11.14
    },
    "STORJ": {
      "weekly_open": 1.35,
      "weekly_close": 1.16,
      "weekly_delta_percentage": -14.07
    },
    "SNX": {
      "weekly_open": 5.79,
      "weekly_close": 4.84,
      "weekly_delta_percentage": -16.41
    },
    "BADGER": {
      "weekly_open": 11.72,
      "weekly_close": 10.78,
      "weekly_delta_percentage": -8.02
    },
    "BTC": {
      "weekly_open": 41559.01,
      "weekly_close": 42296.23,
      "weekly_delta_percentage": 1.77
    },
    "RAD": {
      "weekly_open": 5.62,
      "weekly_close": 5.47,
      "weekly_delta_percentage": -2.67
    },
    "ICP": {
      "weekly_open": 22.76,
      "weekly_close": 19.95,
      "weekly_delta_percentage": -12.35
    },
    "CRO": {
      "weekly_open": 0.4445,
      "weekly_close": 0.486,
      "weekly_delta_percentage": 9.34
    },
    "FIL": {
      "weekly_open": 22.28,
      "weekly_close": 21.04,
      "weekly_delta_percentage": -5.57
    },
    "ETH": {
      "weekly_open": 3027.43,
      "weekly_close": 2928.55,
      "weekly_delta_percentage": -3.27
    },
    "RGT": {
      "weekly_open": 22.24,
      "weekly_close": 19.82,
      "weekly_delta_percentage": -10.88
    }
  },
  "top_by_num_commits": [
    {
      "token": "ICP",
      "count": 211
    },
    {
      "token": "LINK",
      "count": 182
    },
    {
      "token": "XYO",
      "count": 155
    },
    {
      "token": "ETH",
      "count": 135
    },
    {
      "token": "FIL",
      "count": 128
    },
    {
      "token": "OMG",
      "count": 122
    },
    {
      "token": "ALGO",
      "count": 118
    },
    {
      "token": "API3",
      "count": 108
    },
    {
      "token": "LPT",
      "count": 100
    },
    {
      "token": "SOL",
      "count": 84
    }
  ],
  "top_by_new_lines": [
    {
      "token": "ALGO",
      "count": 211493
    },
    {
      "token": "ETH",
      "count": 152522
    },
    {
      "token": "SNX",
      "count": 102422
    },
    {
      "token": "SKL",
      "count": 100141
    },
    {
      "token": "RGT",
      "count": 56637
    },
    {
      "token": "CRO",
      "count": 56626
    },
    {
      "token": "BADGER",
      "count": 53949
    },
    {
      "token": "LPT",
      "count": 50979
    },
    {
      "token": "XYO",
      "count": 47051
    },
    {
      "token": "OMG",
      "count": 46989
    }
  ],
  "top_by_num_distinct_authors": [
    {
      "token": "ICP",
      "count": 40
    },
    {
      "token": "LINK",
      "count": 21
    },
    {
      "token": "ETH",
      "count": 21
    },
    {
      "token": "STORJ",
      "count": 17
    },
    {
      "token": "ALGO",
      "count": 14
    },
    {
      "token": "FIL",
      "count": 11
    },
    {
      "token": "BTC",
      "count": 10
    },
    {
      "token": "SKL",
      "count": 9
    },
    {
      "token": "RAD",
      "count": 8
    },
    {
      "token": "OMG",
      "count": 8
    }
  ]
}